mytests/__init__.py
mytests/filetests.py
mytests-0.1.dist-info/METADATA
mytests-0.1.dist-info/WHEEL
mytests-0.1.dist-info/top_level.txt
mytests-0.1.dist-info/RECORD
