Metadata-Version: 2.1
Name: mytests
Version: 0.1
Summary: test module by Jade
Home-page: https://github.com/indiflex/hello/mytests
Author: Jade IndiFlex
Author-email: indiflex1@gmail.com
License: MIT
Platform: UNKNOWN
Requires-Dist: requests
